imgmagic/__init__.py
imgmagic/colors.py
imgmagic/display.py
imgmagic/filter.py
imgmagic/fourier.py
imgmagic/geometric.py
imgmagic/histogram.py
imgmagic-1.0.dist-info/METADATA
imgmagic-1.0.dist-info/WHEEL
imgmagic-1.0.dist-info/top_level.txt
imgmagic-1.0.dist-info/RECORD
